{
  "Luxury": {
    "totalSeats": 200,
    "window": 100,
    "center": 100,
    "price": 3500,
    "seatPrice": {
      "window": 700,
      "center": 0
    }
  },
  "Buffet": {
    "totalSeats": 200,
    "window": 100,
    "center": 100,
    "price": 2650,
    "seatPrice": {
      "window": 700,
      "center": 0
    }
  },
  "A la carte": {
    "totalSeats": 100,
    "window": 50,
    "center": 50,
    "price": 1750,
    "seatPrice": {
      "window": 700,
      "center": 0
    }
  },
  "Test Cruise Type": {
    "totalSeats": 79,
    "window": 39,
    "center": 40,
    "price": 10,
    "seatPrice": {
      "window": 700,
      "center": 0
    }
  }
}